pysortpack/__init__.py
pysortpack/sort.py
pysortpack-0.0.4.dist-info/LICENSE
pysortpack-0.0.4.dist-info/METADATA
pysortpack-0.0.4.dist-info/WHEEL
pysortpack-0.0.4.dist-info/top_level.txt
pysortpack-0.0.4.dist-info/RECORD
